securecli/__init__.py
securecli/__main__.py
securecli/config.py
securecli/main.py
securecli/workspace.py
securecli/agents/__init__.py
securecli/agents/auditor.py
securecli/agents/base.py
securecli/agents/local_model.py
securecli/agents/planner.py
securecli/agents/refactor.py
securecli/agents/repo.py
securecli/agents/reporter.py
securecli/agents/scanner.py
securecli/analysis/__init__.py
securecli/analysis/cross_file.py
securecli/cli/__init__.py
securecli/cli/commands.py
securecli/cli/completers.py
securecli/cli/formatters.py
securecli/cli/repl.py
securecli/github/__init__.py
securecli/github/analyzer.py
securecli/languages/__init__.py
securecli/languages/detector.py
securecli/modules/__init__.py
securecli/modules/auditor.py
securecli/modules/auditors.py
securecli/modules/base.py
securecli/modules/scanners.py
securecli/modules/tighten.py
securecli/rag/__init__.py
securecli/rag/embeddings.py
securecli/rag/storage.py
securecli/rag/vectorstore.py
securecli/report/__init__.py
securecli/report/cvss.py
securecli/report/diagrams.py
securecli/report/json_export.py
securecli/report/markdown.py
securecli/schemas/__init__.py
securecli/schemas/analysis.py
securecli/schemas/config.py
securecli/schemas/findings.py
securecli/schemas/security.py
securecli/tools/__init__.py
securecli/tools/bandit.py
securecli/tools/base.py
securecli/tools/c_analyzer.py
securecli/tools/cairo_analyzer.py
securecli/tools/clarity_analyzer.py
securecli/tools/cpp_analyzer.py
securecli/tools/csharp_analyzer.py
securecli/tools/dart_flutter_analyzer.py
securecli/tools/erlang_elixir_analyzer.py
securecli/tools/fsharp_analyzer.py
securecli/tools/gitleaks.py
securecli/tools/go_analyzer.py
securecli/tools/gosec.py
securecli/tools/haskell_analyzer.py
securecli/tools/java_analyzer.py
securecli/tools/kotlin_analyzer.py
securecli/tools/lua_analyzer.py
securecli/tools/move_analyzer.py
securecli/tools/npm_audit.py
securecli/tools/objective_c_analyzer.py
securecli/tools/perl_analyzer.py
securecli/tools/php_analyzer.py
securecode_ai-1.0.0.dist-info/METADATA
securecode_ai-1.0.0.dist-info/WHEEL
securecode_ai-1.0.0.dist-info/entry_points.txt
securecode_ai-1.0.0.dist-info/licenses/LICENSE
securecode_ai-1.0.0.dist-info/RECORD
