Metadata-Version: 2.4
Name: securecode-ai
Version: 1.0.0
Summary: AI-Powered Security Analysis CLI with GitHub Integration and Universal Language Support
Project-URL: Homepage, https://github.com/securecli/securecli
Project-URL: Repository, https://github.com/securecli/securecli
Project-URL: Documentation, https://securecli.readthedocs.io
Project-URL: Bug Tracker, https://github.com/securecli/securecli/issues
Author: SecureCLI Team
License-Expression: MIT
License-File: LICENSE
Classifier: Development Status :: 4 - Beta
Classifier: Intended Audience :: Developers
Classifier: License :: OSI Approved :: MIT License
Classifier: Programming Language :: Python :: 3.10
Classifier: Programming Language :: Python :: 3.11
Classifier: Programming Language :: Python :: 3.12
Classifier: Topic :: Security
Classifier: Topic :: Software Development :: Quality Assurance
Classifier: Topic :: Software Development :: Version Control :: Git
Requires-Python: >=3.10
Requires-Dist: aiofiles>=23.0.0
Requires-Dist: art>=6.1
Requires-Dist: blessed>=1.20.0
Requires-Dist: click>=8.0.0
Requires-Dist: colorama>=0.4.6
Requires-Dist: gitpython>=3.1.0
Requires-Dist: jinja2>=3.1.0
Requires-Dist: prompt-toolkit>=3.0.0
Requires-Dist: pydantic>=2.0.0
Requires-Dist: pyfiglet>=1.0.2
Requires-Dist: pyyaml>=6.0.0
Requires-Dist: requests>=2.31.0
Requires-Dist: rich>=13.0.0
Requires-Dist: termcolor>=2.3.0
Requires-Dist: toml>=0.10.0
Provides-Extra: all
Requires-Dist: securecli[ci,dev,infrastructure,mobile,web3]; extra == 'all'
Provides-Extra: ci
Requires-Dist: github-actions-runner>=1.0.0; extra == 'ci'
Provides-Extra: dev
Requires-Dist: black>=23.0.0; extra == 'dev'
Requires-Dist: flake8>=6.0.0; extra == 'dev'
Requires-Dist: isort>=5.12.0; extra == 'dev'
Requires-Dist: mypy>=1.5.0; extra == 'dev'
Requires-Dist: pre-commit>=3.0.0; extra == 'dev'
Requires-Dist: pytest-asyncio>=0.21.0; extra == 'dev'
Requires-Dist: pytest-cov>=4.0.0; extra == 'dev'
Requires-Dist: pytest-mock>=3.11.0; extra == 'dev'
Requires-Dist: pytest>=7.0.0; extra == 'dev'
Provides-Extra: infrastructure
Requires-Dist: ansible>=7.0.0; extra == 'infrastructure'
Requires-Dist: kubernetes>=27.0.0; extra == 'infrastructure'
Requires-Dist: terraform>=1.0.0; extra == 'infrastructure'
Provides-Extra: mobile
Requires-Dist: android-lint>=1.0.0; extra == 'mobile'
Requires-Dist: xcrun>=1.0.0; extra == 'mobile'
Provides-Extra: web3
Requires-Dist: brownie>=1.19.0; extra == 'web3'
Requires-Dist: mythril>=0.24.0; extra == 'web3'
Requires-Dist: slither-analyzer>=0.10.0; extra == 'web3'
Requires-Dist: web3>=6.0.0; extra == 'web3'
